cdst/__init__.py
cdst/cspd.py
cdst/dnn.py
cdst/ohpl.py
cdst/shared.py
cdst-0.1.dist-info/LICENSE
cdst-0.1.dist-info/METADATA
cdst-0.1.dist-info/WHEEL
cdst-0.1.dist-info/top_level.txt
cdst-0.1.dist-info/RECORD
