Metadata-Version: 2.1
Name: cdst
Version: 0.1
Summary: Calvin's Data Science Toolbox
Home-page: https://github.com/Bayer-Group/cdst
Author: Dr. Calvin Chan
Author-email: calvin.chan@bayer.com
License: UNKNOWN
Project-URL: Bug Tracker, https://github.com/Bayer-Group/cdst/issues
Keywords: deep learning,hyperparameter
Platform: UNKNOWN
Classifier: Programming Language :: Python :: 3
Classifier: License :: OSI Approved :: BSD License
Classifier: Operating System :: OS Independent
Requires-Python: >=3.8
License-File: LICENSE
Requires-Dist: cython (>="0.29.24")
Requires-Dist: numpy (>="1.20.0")
Requires-Dist: scikit-learn
Requires-Dist: pandas
Requires-Dist: torch (>="1.9.0")
Requires-Dist: skorch
Requires-Dist: ray (>="1.12.0")
Requires-Dist: tensorboardX
Requires-Dist: gekko (>="1.0.2")
Requires-Dist: tensorflow
